atk_training_dinesh_wf_dynamic_loader/__init__.py
atk_training_dinesh_wf_dynamic_loader-0.1.0.dist-info/METADATA
atk_training_dinesh_wf_dynamic_loader-0.1.0.dist-info/WHEEL
atk_training_dinesh_wf_dynamic_loader-0.1.0.dist-info/entry_points.txt
atk_training_dinesh_wf_dynamic_loader-0.1.0.dist-info/RECORD
