Metadata-Version: 2.1
Name: atk-training-dinesh-wf-dynamic-loader
Version: 0.1.0
Summary: 
Author: dinesh-acog
Author-email: dinesh@aganitha.ai
Requires-Python: >=3.11,<4.0
Classifier: Programming Language :: Python :: 3
Classifier: Programming Language :: Python :: 3.11
Classifier: Programming Language :: Python :: 3.12
Requires-Dist: importlib (>=1.0.4,<2.0.0)
Requires-Dist: logging (>=0.4.9.6,<0.5.0.0)
Requires-Dist: pathlib (>=1.0.1,<2.0.0)
Requires-Dist: pyyaml (>=6.0.1,<7.0.0)
Requires-Dist: typer (>=0.9.0,<0.10.0)
